setup.py
eurdep/__init__.py
eurdep.egg-info/PKG-INFO
eurdep.egg-info/SOURCES.txt
eurdep.egg-info/dependency_links.txt
eurdep.egg-info/top_level.txt