Metadata-Version: 1.0
Name: eurdep
Version: 0.7
Summary: Parser for Eurdep messages, which are used for measuring gamma radiation
Home-page: http://github.com/palli/eurdep
Author: Pall Sigurdsson
Author-email: palli@opensource.is
License: GPL
Platform: UNKNOWN
